{
  "name": "Sunset Mirage",
  "description": "A warm, glowing scene inspired by sunsets and desert mirages, with smooth morphing and gentle movement.",
  "timestamp": "2025-07-31T20:00:00.000Z",
  "version": "1.0",
  "settings": {
    "animationType": 1,
    "animationSpeed": 0.18,
    "enableShapeCycling": true,
    "enableSizeAnimation": true,
    "movementAmplitude": 0.22,
    "movementFrequency": 0.28,
    "rotationAmplitude": 0.12,
    "rotationFrequency": 0.18,
    "scaleAmplitude": 0.09,
    "scaleFrequency": 0.13,
    "shapeCyclingSpeed": 0.22,
    "shapeCyclingPattern": 1,
    "shapeCyclingDirection": 0,
    "shapeCyclingSync": 0,
    "shapeCyclingIntensity": 0.7,
    "shapeCyclingTrigger": 0,
    "morphingEnabled": true,
    "morphingSpeed": 0.22,
    "morphingEasing": "sine.inOut",
    "autoMorphing": true,
    "crossCategoryMorphing": false,
    "morphingAggressiveness": 0.5,
    "currentMorphProgress": 0,
    "morphingPreset": "organic_flow",
    "randomMorphing": true,
    "morphingTargetShape": null,
    "gridWidth": 10,
    "gridHeight": 7,
    "cellSize": 1.1,
    "compositionWidth": 22,
    "compositionHeight": 22,
    "showGrid": false,
    "randomness": 0.6,
    "shapeColor": "#ffb347",
    "backgroundColor": "#2d1a32",
    "enabledShapes": {
      "Basic Shapes": true,
      "Triangles": false,
      "Rectangles": true,
      "Ellipses": true,
      "Refractive Spheres": true
    },
    "sphereRefraction": 1.6,
    "sphereTransparency": 0.7,
    "sphereRoughness": 0.18,
    "sphereMetalness": 0.08,
    "sphereTransmission": 0.4,
    "sphereScale": 1.1,
    "sphereClearcoat": 0.12,
    "sphereClearcoatRoughness": 0.09,
    "sphereEnvMapIntensity": 0.3,
    "sphereWaterDistortion": false,
    "sphereDistortionStrength": 0.1,
    "postProcessingEnabled": true,
    "bloomEnabled": true,
    "bloomStrength": 0.18,
    "bloomRadius": 0.12,
    "bloomThreshold": 0.7,
    "vignetteEnabled": true,
    "vignetteIntensity": 0.22,
    "vignetteRadius": 0.5,
    "vignetteSoftness": 0.5,
    "grainEnabled": true,
    "grainIntensity": 0.1,
    "colorGradingEnabled": false,
    "colorHue": 0,
    "colorSaturation": 1,
    "colorBrightness": 1,
    "colorContrast": 1,
    "fxaaEnabled": true,
    "ambientLightIntensity": 0.97,
    "directionalLightIntensity": 0.04,
    "pointLight1Intensity": 2.94,
    "pointLight2Intensity": 3,
    "rimLightIntensity": 3,
    "accentLightIntensity": 2.97,
    "enableFrustumCulling": true,
    "centerScalingEnabled": false,
    "centerScalingIntensity": 0.5,
    "centerScalingCurve": 0,
    "centerScalingRadius": 1.0,
    "centerScalingDirection": 0,
    "centerScalingAnimation": false,
    "centerScalingAnimationSpeed": 1.0,
    "centerScalingAnimationType": 0
  }
}
